google_datacatalog_postgresql_connector-0.10.0-py3.8-nspkg.pth
google/datacatalog_connectors/postgresql/__init__.py
google/datacatalog_connectors/postgresql/datacatalog_cli.py
google/datacatalog_connectors/postgresql/config/__init__.py
google/datacatalog_connectors/postgresql/config/metadata_definition.json
google/datacatalog_connectors/postgresql/config/metadata_query.sql
google/datacatalog_connectors/postgresql/config/num_rows_query.sql
google/datacatalog_connectors/postgresql/scrape/__init__.py
google/datacatalog_connectors/postgresql/scrape/metadata_scraper.py
google/datacatalog_connectors/postgresql/scrape/query_assembler.py
google_datacatalog_postgresql_connector-0.10.0.dist-info/METADATA
google_datacatalog_postgresql_connector-0.10.0.dist-info/WHEEL
google_datacatalog_postgresql_connector-0.10.0.dist-info/entry_points.txt
google_datacatalog_postgresql_connector-0.10.0.dist-info/namespace_packages.txt
google_datacatalog_postgresql_connector-0.10.0.dist-info/top_level.txt
google_datacatalog_postgresql_connector-0.10.0.dist-info/RECORD
